ez_emoji/__init__.py
ez_emoji/curation.py
ez_emoji/downloader.py
ez_emoji/emoji_log.py
ez_emoji/utils.py
ez_emoji/sentiment/gen_sentiment.py
ez_emoji/sentiment/sentiment.py
ez_emoji-0.1.13.dist-info/LICENSE
ez_emoji-0.1.13.dist-info/METADATA
ez_emoji-0.1.13.dist-info/WHEEL
ez_emoji-0.1.13.dist-info/entry_points.txt
ez_emoji-0.1.13.dist-info/top_level.txt
ez_emoji-0.1.13.dist-info/RECORD
