Metadata-Version: 2.1
Name: ez-emoji
Version: 0.1.13
Summary: Download the latest emoji data from unicode.  Also several utility functions to use emojis as well as an emoji log formatter.
License: MIT
Project-URL: homepage, https://github.com/jthop/ez-emoji
Project-URL: repository, https://github.com/jthop/ez-emoji
Keywords: api,auth
Classifier: Development Status :: 5 - Production/Stable
Classifier: License :: OSI Approved :: MIT License
License-File: LICENSE
Requires-Dist: importlib-metadata ; python_version < "3.8"
